{
  "multipart": [
    {
      "apply": {
        "model": "pantographsandwires:block/cantilever_bracket/base_oxidized"
      },
      "when": {
        "facing": "north"
      }
    },
    {
      "apply": {
        "model": "pantographsandwires:block/cantilever_bracket/base_oxidized",
        "y": 90
      },
      "when": {
        "facing": "east"
      }
    },
    {
      "apply": {
        "model": "pantographsandwires:block/cantilever_bracket/base_oxidized",
        "y": 180
      },
      "when": {
        "facing": "south"
      }
    },
    {
      "apply": {
        "model": "pantographsandwires:block/cantilever_bracket/base_oxidized",
        "y": 270
      },
      "when": {
        "facing": "west"
      }
    },
    {
      "apply": {
        "model": "pantographsandwires:block/cantilever_bracket/crossing_post_part_oxidized"
      },
      "when": {
        "up": "true"
      }
    },
    {
      "apply": {
        "model": "pantographsandwires:block/cantilever_bracket/crossing_post_part_oxidized",
        "x": 180
      },
      "when": {
        "down": "true"
      }
    },
    {
      "apply": {
        "model": "pantographsandwires:block/cantilever_bracket/t_cross_oxidized"
      },
      "when": {
        "down": "true",
        "facing": "north",
        "up": "false"
      }
    },
    {
      "apply": {
        "model": "pantographsandwires:block/cantilever_bracket/t_cross_oxidized",
        "y": 90
      },
      "when": {
        "down": "true",
        "facing": "east",
        "up": "false"
      }
    },
    {
      "apply": {
        "model": "pantographsandwires:block/cantilever_bracket/t_cross_oxidized",
        "y": 180
      },
      "when": {
        "down": "true",
        "facing": "south",
        "up": "false"
      }
    },
    {
      "apply": {
        "model": "pantographsandwires:block/cantilever_bracket/t_cross_oxidized",
        "y": 270
      },
      "when": {
        "down": "true",
        "facing": "west",
        "up": "false"
      }
    },
    {
      "apply": {
        "model": "pantographsandwires:block/cantilever_bracket/t_cross_oxidized",
        "x": 180
      },
      "when": {
        "down": "false",
        "facing": "north",
        "up": "true"
      }
    },
    {
      "apply": {
        "model": "pantographsandwires:block/cantilever_bracket/t_cross_oxidized",
        "x": 180,
        "y": 90
      },
      "when": {
        "down": "false",
        "facing": "east",
        "up": "true"
      }
    },
    {
      "apply": {
        "model": "pantographsandwires:block/cantilever_bracket/t_cross_oxidized",
        "x": 180,
        "y": 180
      },
      "when": {
        "down": "false",
        "facing": "south",
        "up": "true"
      }
    },
    {
      "apply": {
        "model": "pantographsandwires:block/cantilever_bracket/t_cross_oxidized",
        "x": 180,
        "y": 270
      },
      "when": {
        "down": "false",
        "facing": "west",
        "up": "true"
      }
    },
    {
      "apply": {
        "model": "pantographsandwires:block/cantilever_bracket/cross_oxidized"
      },
      "when": {
        "down": "true",
        "facing": "north",
        "up": "true"
      }
    },
    {
      "apply": {
        "model": "pantographsandwires:block/cantilever_bracket/cross_oxidized",
        "y": 90
      },
      "when": {
        "down": "true",
        "facing": "east",
        "up": "true"
      }
    },
    {
      "apply": {
        "model": "pantographsandwires:block/cantilever_bracket/cross_oxidized",
        "y": 180
      },
      "when": {
        "down": "true",
        "facing": "south",
        "up": "true"
      }
    },
    {
      "apply": {
        "model": "pantographsandwires:block/cantilever_bracket/cross_oxidized",
        "y": 270
      },
      "when": {
        "down": "true",
        "facing": "west",
        "up": "true"
      }
    }
  ]
}